code_cartographer/__init__.py
code_cartographer/cli.py
code_cartographer/core/analyzer.py
code_cartographer/core/variant_analyzer.py
code_cartographer-0.2.1.dist-info/METADATA
code_cartographer-0.2.1.dist-info/WHEEL
code_cartographer-0.2.1.dist-info/licenses/LICENSE
code_cartographer-0.2.1.dist-info/RECORD
