Metadata-Version: 2.4
Name: code-cartographer
Version: 0.2.1
Summary: A tool for visualizing and analyzing code repositories
Project-URL: Homepage, https://github.com/stochastic-sisyphus
Project-URL: Repository, https://github.com/stochastic-sisyphus/code-cartographer
Project-URL: Documentation, https://github.com/stochastic-sisyphus/code-cartographer#readme
Project-URL: Bug Tracker, https://github.com/stochastic-sisyphus/code-cartographer/issues
Author: Vanessa Beck
License-Expression: MIT
License-File: LICENSE
Keywords: analysis,code,visualization
Classifier: Development Status :: 3 - Alpha
Classifier: Intended Audience :: Developers
Classifier: License :: OSI Approved :: MIT License
Classifier: Programming Language :: Python :: 3
Classifier: Programming Language :: Python :: 3.8
Classifier: Programming Language :: Python :: 3.9
Classifier: Programming Language :: Python :: 3.10
Classifier: Programming Language :: Python :: 3.11
Requires-Python: >=3.8
Requires-Dist: click>=8.1.0
Requires-Dist: nltk>=3.8.1
Requires-Dist: python-dotenv>=1.0.0
Requires-Dist: pyyaml>=6.0.0
Requires-Dist: requests>=2.28.0
Requires-Dist: rich>=13.0.0
Requires-Dist: sentence-transformers>=2.2.2
Provides-Extra: dev
Requires-Dist: black>=23.0.0; extra == 'dev'
Requires-Dist: flake8>=6.0.0; extra == 'dev'
Requires-Dist: isort>=5.12.0; extra == 'dev'
Requires-Dist: mypy>=1.0.0; extra == 'dev'
Requires-Dist: pre-commit>=3.0.0; extra == 'dev'
Requires-Dist: pytest-cov>=4.0.0; extra == 'dev'
Requires-Dist: pytest>=7.0.0; extra == 'dev'
Provides-Extra: test
Requires-Dist: pytest-cov>=4.0.0; extra == 'test'
Requires-Dist: pytest>=7.0.0; extra == 'test'
